{
	"merchantSku": "ABC-123",
	"productTitle": "My Product",
	"jetBrowseNodeId": "100",
	"standardProductCode": "1234567890123",
	"standardProductCodeType": "UPC",
	"multipackQuantity": 6,
	"brand": "My Product's Brand",
	"manufacturer": "My Product's Manufacturer",
	"mfrPartNumber": "AB-9874",
	"productDescription": "This is a terrific product that everyone should own.",
	"bullet1": "Bullet Point 1",
	"bullet2": "Bullet Point 2",
	"bullet3": "Bullet Point 3",
	"bullet4": "Bullet Point 4",
	"bullet5": "Bullet Point 5",
	"numberUnitsForPricePerUnit": 1,
	"typeOfUnitForPricePerUnit": "each",
	"shippingWeightPounds": 10,
	"packageLengthInches": 12,
	"packageWidthInches": 12,
	"packageHeightInches": 12,
	"parentOrChild": "Child",
	"parentSku": "AB-122",
	"relationship": "Variation",
	"variationRefinements": "color",
	"prop65": true,
	"legalDisclaimerDescription": "Legal stuff goes here",
	"cpsiaCautionaryStatement1": "Cautionary Statement Line 1",
	"cpsiaCautionaryStatement2": "Cautionary Statement Line 2",
	"cpsiaCautionaryStatement3": "Cautionary Statement Line 3",
	"cpsiaCautionaryStatement4": "Cautionary Statement Line 4",
	"countryOfOrigin": "U.S.A.",
	"safetyWarning": "warning text goes here"
}